<?xml version="1.0" encoding="UTF-8"?>

  <deviceConfig>
    <libraries>
      <file>myfile.h</file>
    </libraries>

      <field type="unsignedIntField">
        <title>A number</title>
        <description>
          A number for use in the program.
        </description>
        <value>32</value>
      </field>

      <field type="signedIntField">
        <title>A number</title>
        <description>
          A number for use in the program.
        </description>
        <value>-12</value>
      </field>

      <field type="signedIntField">
        <title>A number</title>
        <description>
          A number for use in the program.
        </description>
        <value>64</value>
      </field>

      <field type="shortField">
        <title>A number</title>
        <description>
          A number for use in the program.
        </description>
        <value>100</value>
      </field>

      <field type="floatField">
        <title>A number</title>
        <description>
          A number for use in the program.
        </description>
        <value>22.33f</value>
      </field>

      <field type="doubleField">
        <title>A number</title>
        <description>
          A number for use in the program.
        </description>
        <value>3.14</value>
      </field>

      <field type="stringField">
        <title>A string</title>
        <description>
          A string for use in the program.
        </description>
        <value>hello</value>
      </field>

  </deviceConfig>
